context_nexus/__init__.py
context_nexus/_core.cpython-312-x86_64-linux-gnu.so
context_nexus/agents/__init__.py
context_nexus/agents/agent.py
context_nexus/context/__init__.py
context_nexus/core/__init__.py
context_nexus/core/config.py
context_nexus/core/nexus.py
context_nexus/core/types.py
context_nexus/ingestion/__init__.py
context_nexus/ingestion/chunker.py
context_nexus/ingestion/embedder.py
context_nexus/ingestion/indexer.py
context_nexus/ingestion/loader.py
context_nexus/observability/__init__.py
context_nexus/observability/tracer.py
context_nexus/retrieval/__init__.py
context_nexus/retrieval/hybrid.py
context_nexus-1.0.0.dist-info/METADATA
context_nexus-1.0.0.dist-info/WHEEL
context_nexus-1.0.0.dist-info/licenses/LICENSE
context_nexus-1.0.0.dist-info/RECORD
