Metadata-Version: 2.4
Name: context-nexus
Version: 1.0.0
Classifier: Development Status :: 3 - Alpha
Classifier: Intended Audience :: Developers
Classifier: License :: OSI Approved :: MIT License
Classifier: Programming Language :: Python :: 3
Classifier: Programming Language :: Python :: 3.10
Classifier: Programming Language :: Python :: 3.11
Classifier: Programming Language :: Python :: 3.12
Classifier: Programming Language :: Rust
Requires-Dist: pydantic>=2.0
Requires-Dist: httpx>=0.25
Requires-Dist: tenacity>=8.0
Requires-Dist: anyio>=4.0
Requires-Dist: numpy>=1.24
Requires-Dist: networkx>=3.0
Requires-Dist: openai>=1.0
Requires-Dist: tiktoken>=0.5
Requires-Dist: python-dotenv>=1.0
Requires-Dist: rich>=13.0
Requires-Dist: pypdf>=3.0
Requires-Dist: pytest>=7.0 ; extra == 'dev'
Requires-Dist: pytest-asyncio>=0.21 ; extra == 'dev'
Requires-Dist: pytest-cov>=4.0 ; extra == 'dev'
Requires-Dist: ruff>=0.1 ; extra == 'dev'
Requires-Dist: mypy>=1.0 ; extra == 'dev'
Requires-Dist: maturin>=1.4 ; extra == 'dev'
Requires-Dist: sentence-transformers>=2.2 ; extra == 'local'
Requires-Dist: qdrant-client>=1.7 ; extra == 'production'
Requires-Dist: neo4j>=5.0 ; extra == 'production'
Requires-Dist: redis>=5.0 ; extra == 'production'
Requires-Dist: faiss-cpu>=1.7 ; extra == 'vector'
Provides-Extra: dev
Provides-Extra: local
Provides-Extra: production
Provides-Extra: vector
License-File: LICENSE
Summary: SDK for building agentic AI systems
Keywords: ai,llm,rag,agents
Author-email: Chiraag Kakar <connect.with.chiraag@gmail.com>
License: MIT
Requires-Python: >=3.10
Project-URL: Homepage, https://github.com/chiraag-kakar/context-nexus
Project-URL: Repository, https://github.com/chiraag-kakar/context-nexus
